FairRankTune/__init__.py
FairRankTune/Metrics/ARP.py
FairRankTune/Metrics/AWRF.py
FairRankTune/Metrics/ComboUtil.py
FairRankTune/Metrics/ERB.py
FairRankTune/Metrics/EXP.py
FairRankTune/Metrics/IAA.py
FairRankTune/Metrics/NDKL.py
FairRankTune/Metrics/__init__.py
FairRankTune/RankTune/__init__.py
FairRankTune/RankTune/src.py
FairRankTune/Rankers/DetConstSort_Geyiketal.py
FairRankTune/Rankers/EpsilonGreedy_Fengetal.py
FairRankTune/Rankers/__init__.py
fairranktune-0.0.6.dist-info/METADATA
fairranktune-0.0.6.dist-info/WHEEL
fairranktune-0.0.6.dist-info/licenses/LICENSE
fairranktune-0.0.6.dist-info/RECORD
