Metadata-Version: 2.1
Name: FairRankTune
Version: 0.0.6
Summary: FairRankTune a python pacakage for fairness-aware data generation, metrics, and algorithms.
Project-URL: homepage, https://kcachel.github.io/
Project-URL: repository, https://github.com/KCachel/FairRankTune
Project-URL: documentation, https://github.com/KCachel/FairRankTune
Author-email: Kathleen Cachel <kathleen.cachel@gmail.com>
License-File: LICENSE
Classifier: License :: OSI Approved :: BSD License
Classifier: Operating System :: OS Independent
Classifier: Programming Language :: Python :: 3
Requires-Python: >=3.9
